<?xml version="1.0" encoding="UTF-8"?>
<root>
    <flow>
        <demand>200</demand>
        <startTime>0</startTime>
        <endTime>10</endTime>
        <source>1</source>
        <destination>12</destination>
        <!--
        V = 2000
        end = 20
        -->
    </flow>
    <flow>
        <demand>20</demand>
        <startTime>20</startTime>
        <endTime>22</endTime>
        <source>1</source>
        <destination>12</destination>
        <!--
        V = 40
        end = 22
        -->
    </flow>
    <flow>
        <demand>20</demand>
        <startTime>20</startTime>
        <endTime>22</endTime>
        <source>11</source>
        <destination>12</destination>
        <!--
        V = 40
        end = 22
        -->
    </flow>

    <flow>
        <demand>60</demand>
        <startTime>23</startTime>
        <endTime>24</endTime>
        <source>11</source>
        <destination>12</destination>
        <!--
        V = 60
        end = 24.2
        -->
    </flow>
    <flow>
        <demand>60</demand>
        <startTime>23</startTime>
        <endTime>24</endTime>
        <source>11</source>
        <destination>10</destination>
        <!--
        V = 60
        end = 24.2
        -->
    </flow>

    <flow>
        <demand>150</demand>
        <startTime>25</startTime>
        <endTime>26</endTime>
        <source>11</source>
        <destination>12</destination>
        <!--
        V = 150
        end = 28
        -->
    </flow>
    <flow>
        <demand>150</demand>
        <startTime>25</startTime>
        <endTime>26</endTime>
        <source>11</source>
        <destination>10</destination>
        <!--
        V = 150
        end = 28
        -->
    </flow>
    
    <flow>
        <demand>150</demand>
        <startTime>29</startTime>
        <endTime>30</endTime>
        <source>11</source>
        <destination>12</destination>
        <!--
        V = 150
        end = 32
        -->
    </flow>
    <flow>
        <demand>150</demand>
        <startTime>29</startTime>
        <endTime>30</endTime>
        <source>11</source>
        <destination>10</destination>
        <!--
        V = 150
        end = 32
        -->
    </flow>
    <flow>
        <demand>100</demand>
        <startTime>29</startTime>
        <endTime>30</endTime>
        <source>2</source>
        <destination>1</destination>
        <!--
        V = 100
        end = 30
        -->
    </flow>
    
    <flow>
        <demand>80</demand>
        <startTime>40</startTime>
        <endTime>43</endTime>
        <source>1</source>
        <destination>6</destination>
        <!--
        V = 240
        end = 43.75
        -->
    </flow>
    <flow>
        <demand>100</demand>
        <startTime>41</startTime>
        <endTime>42</endTime>
        <source>8</source>
        <destination>4</destination>
        <!--
        V = 100
        end = 43
        -->
    </flow>    
    <flow>
        <demand>10</demand>
        <startTime>42</startTime>
        <endTime>43</endTime>
        <source>11</source>
        <destination>2</destination>
        <!--
        V = 10
        end = 43
        -->
    </flow>
    
    <flow>
        <demand>80</demand>
        <startTime>50</startTime>
        <endTime>53</endTime>
        <source>1</source>
        <destination>6</destination>
        <!--
        V = 240
        end = 53
        -->
    </flow>
    <flow>
        <demand>100</demand>
        <startTime>51</startTime>
        <endTime>52</endTime>
        <source>4</source>
        <destination>8</destination>
        <!--
        V = 100
        end = 52
        -->
    </flow>    
    <flow>
        <demand>10</demand>
        <startTime>52</startTime>
        <endTime>53</endTime>
        <source>11</source>
        <destination>2</destination>
        <!--
        V = 10
        end = 53
        -->
    </flow>     

</root>

